streamside/__init__.py
streamside/annotator.py
streamside/json_to_penman.py
streamside/penman_to_json.py
streamside/struct.py
streamside/uitls.py
streamside/resources/__init__.py
streamside/resources/amr/__init__.py
streamside/resources/amr/concepts.json
streamside/resources/amr/relations.json
streamside/resources/wisen/__init__.py
streamside/resources/wisen/concepts.json
streamside/resources/wisen/relations.json
streamside/resources/wiser/__init__.py
streamside/resources/wiser/concepts.json
streamside/resources/wiser/relations.json
streamside/tests/__init__.py
streamside/tests/test_struct.py
streamside-0.5.dist-info/LICENSE
streamside-0.5.dist-info/METADATA
streamside-0.5.dist-info/WHEEL
streamside-0.5.dist-info/top_level.txt
streamside-0.5.dist-info/RECORD
