Metadata-Version: 2.1
Name: streamside
Version: 0.5
Summary: Meaning Representation Annotation Toolkit
Home-page: https://github.com/emorynlp/StreamSide
Author: Jinho D. Choi
Author-email: jinho.choi@emory.edu
License: UNKNOWN
Platform: UNKNOWN
Classifier: Programming Language :: Python :: 3
Classifier: License :: OSI Approved :: Apache Software License
Classifier: Operating System :: OS Independent
Requires-Dist: PyQt5 (==5.15.4)
